{"timestamp": 1744258269.2801712, "key_args_repr": "['prices', 'T5_FIBER,T5_HIDE,T5_ORE,T5_ROCK,T5_WOOD', 'Black Market,Bridgewatch,Caerleon,Fort Sterling,Lymhurst,Martlock,Thetford', '1']", "data": [{"item_id": "T5_FIBER", "city": "Black Market", "quality": 1, "sell_price_min": 0, "sell_price_min_date": "0001-01-01T00:00:00", "sell_price_max": 0, "sell_price_max_date": "0001-01-01T00:00:00", "buy_price_min": 0, "buy_price_min_date": "0001-01-01T00:00:00", "buy_price_max": 0, "buy_price_max_date": "0001-01-01T00:00:00"}, {"item_id": "T5_FIBER", "city": "Bridgewatch", "quality": 1, "sell_price_min": 258, "sell_price_min_date": "2025-04-09T22:40:00", "sell_price_max": 279, "sell_price_max_date": "2025-04-09T22:40:00", "buy_price_min": 1, "buy_price_min_date": "2025-04-09T22:40:00", "buy_price_max": 257, "buy_price_max_date": "2025-04-09T22:40:00"}, {"item_id": "T5_FIBER", "city": "Caerleon", "quality": 1, "sell_price_min": 288, "sell_price_min_date": "2025-04-09T15:05:00", "sell_price_max": 314, "sell_price_max_date": "2025-04-09T15:05:00", "buy_price_min": 0, "buy_price_min_date": "0001-01-01T00:00:00", "buy_price_max": 0, "buy_price_max_date": "0001-01-01T00:00:00"}, {"item_id": "T5_FIBER", "city": "Fort Sterling", "quality": 1, "sell_price_min": 188, "sell_price_min_date": "2025-04-09T19:30:00", "sell_price_max": 188, "sell_price_max_date": "2025-04-09T19:30:00", "buy_price_min": 5, "buy_price_min_date": "2025-04-09T13:05:00", "buy_price_max": 200, "buy_price_max_date": "2025-04-09T13:05:00"}, {"item_id": "T5_FIBER", "city": "Lymhurst", "quality": 1, "sell_price_min": 297, "sell_price_min_date": "2025-04-10T02:40:00", "sell_price_max": 360, "sell_price_max_date": "2025-04-10T02:40:00", "buy_price_min": 183, "buy_price_min_date": "2025-04-10T02:30:00", "buy_price_max": 282, "buy_price_max_date": "2025-04-10T02:30:00"}, {"item_id": "T5_FIBER", "city": "Martlock", "quality": 1, "sell_price_min": 0, "sell_price_min_date": "0001-01-01T00:00:00", "sell_price_max": 0, "sell_price_max_date": "0001-01-01T00:00:00", "buy_price_min": 0, "buy_price_min_date": "0001-01-01T00:00:00", "buy_price_max": 0, "buy_price_max_date": "0001-01-01T00:00:00"}, {"item_id": "T5_FIBER", "city": "Thetford", "quality": 1, "sell_price_min": 255, "sell_price_min_date": "2025-04-10T00:05:00", "sell_price_max": 284, "sell_price_max_date": "2025-04-10T00:05:00", "buy_price_min": 5, "buy_price_min_date": "2025-04-09T08:30:00", "buy_price_max": 253, "buy_price_max_date": "2025-04-09T08:30:00"}, {"item_id": "T5_HIDE", "city": "Black Market", "quality": 1, "sell_price_min": 319, "sell_price_min_date": "2025-04-10T02:35:00", "sell_price_max": 319, "sell_price_max_date": "2025-04-10T02:35:00", "buy_price_min": 0, "buy_price_min_date": "0001-01-01T00:00:00", "buy_price_max": 0, "buy_price_max_date": "0001-01-01T00:00:00"}, {"item_id": "T5_HIDE", "city": "Bridgewatch", "quality": 1, "sell_price_min": 401, "sell_price_min_date": "2025-04-10T00:35:00", "sell_price_max": 401, "sell_price_max_date": "2025-04-10T00:35:00", "buy_price_min": 1, "buy_price_min_date": "2025-04-09T20:30:00", "buy_price_max": 394, "buy_price_max_date": "2025-04-09T20:30:00"}, {"item_id": "T5_HIDE", "city": "Caerleon", "quality": 1, "sell_price_min": 313, "sell_price_min_date": "2025-04-09T15:15:00", "sell_price_max": 387, "sell_price_max_date": "2025-04-09T15:15:00", "buy_price_min": 0, "buy_price_min_date": "0001-01-01T00:00:00", "buy_price_max": 0, "buy_price_max_date": "0001-01-01T00:00:00"}, {"item_id": "T5_HIDE", "city": "Fort Sterling", "quality": 1, "sell_price_min": 392, "sell_price_min_date": "2025-04-10T03:15:00", "sell_price_max": 415, "sell_price_max_date": "2025-04-10T03:15:00", "buy_price_min": 24, "buy_price_min_date": "2025-04-10T03:15:00", "buy_price_max": 385, "buy_price_max_date": "2025-04-10T03:15:00"}, {"item_id": "T5_HIDE", "city": "Lymhurst", "quality": 1, "sell_price_min": 385, "sell_price_min_date": "2025-04-10T03:10:00", "sell_price_max": 396, "sell_price_max_date": "2025-04-10T03:10:00", "buy_price_min": 17, "buy_price_min_date": "2025-04-10T03:10:00", "buy_price_max": 384, "buy_price_max_date": "2025-04-10T03:10:00"}, {"item_id": "T5_HIDE", "city": "Martlock", "quality": 1, "sell_price_min": 480, "sell_price_min_date": "2025-04-09T23:45:00", "sell_price_max": 499, "sell_price_max_date": "2025-04-09T23:45:00", "buy_price_min": 62, "buy_price_min_date": "2025-04-09T05:25:00", "buy_price_max": 448, "buy_price_max_date": "2025-04-09T05:25:00"}, {"item_id": "T5_HIDE", "city": "Thetford", "quality": 1, "sell_price_min": 425, "sell_price_min_date": "2025-04-09T20:40:00", "sell_price_max": 425, "sell_price_max_date": "2025-04-09T20:40:00", "buy_price_min": 2, "buy_price_min_date": "2025-04-09T11:15:00", "buy_price_max": 394, "buy_price_max_date": "2025-04-09T11:15:00"}, {"item_id": "T5_ORE", "city": "Black Market", "quality": 1, "sell_price_min": 0, "sell_price_min_date": "0001-01-01T00:00:00", "sell_price_max": 0, "sell_price_max_date": "0001-01-01T00:00:00", "buy_price_min": 0, "buy_price_min_date": "0001-01-01T00:00:00", "buy_price_max": 0, "buy_price_max_date": "0001-01-01T00:00:00"}, {"item_id": "T5_ORE", "city": "Bridgewatch", "quality": 1, "sell_price_min": 0, "sell_price_min_date": "0001-01-01T00:00:00", "sell_price_max": 0, "sell_price_max_date": "0001-01-01T00:00:00", "buy_price_min": 0, "buy_price_min_date": "0001-01-01T00:00:00", "buy_price_max": 0, "buy_price_max_date": "0001-01-01T00:00:00"}, {"item_id": "T5_ORE", "city": "Caerleon", "quality": 1, "sell_price_min": 0, "sell_price_min_date": "0001-01-01T00:00:00", "sell_price_max": 0, "sell_price_max_date": "0001-01-01T00:00:00", "buy_price_min": 0, "buy_price_min_date": "0001-01-01T00:00:00", "buy_price_max": 0, "buy_price_max_date": "0001-01-01T00:00:00"}, {"item_id": "T5_ORE", "city": "Fort Sterling", "quality": 1, "sell_price_min": 333, "sell_price_min_date": "2025-04-10T02:20:00", "sell_price_max": 333, "sell_price_max_date": "2025-04-10T02:20:00", "buy_price_min": 27, "buy_price_min_date": "2025-04-09T23:25:00", "buy_price_max": 301, "buy_price_max_date": "2025-04-09T23:25:00"}, {"item_id": "T5_ORE", "city": "Lymhurst", "quality": 1, "sell_price_min": 301, "sell_price_min_date": "2025-04-09T21:45:00", "sell_price_max": 599, "sell_price_max_date": "2025-04-09T21:45:00", "buy_price_min": 200, "buy_price_min_date": "2025-04-09T22:00:00", "buy_price_max": 300, "buy_price_max_date": "2025-04-09T22:00:00"}, {"item_id": "T5_ORE", "city": "Martlock", "quality": 1, "sell_price_min": 0, "sell_price_min_date": "0001-01-01T00:00:00", "sell_price_max": 0, "sell_price_max_date": "0001-01-01T00:00:00", "buy_price_min": 0, "buy_price_min_date": "0001-01-01T00:00:00", "buy_price_max": 0, "buy_price_max_date": "0001-01-01T00:00:00"}, {"item_id": "T5_ORE", "city": "Thetford", "quality": 1, "sell_price_min": 0, "sell_price_min_date": "0001-01-01T00:00:00", "sell_price_max": 0, "sell_price_max_date": "0001-01-01T00:00:00", "buy_price_min": 0, "buy_price_min_date": "0001-01-01T00:00:00", "buy_price_max": 0, "buy_price_max_date": "0001-01-01T00:00:00"}, {"item_id": "T5_ROCK", "city": "Black Market", "quality": 1, "sell_price_min": 0, "sell_price_min_date": "0001-01-01T00:00:00", "sell_price_max": 0, "sell_price_max_date": "0001-01-01T00:00:00", "buy_price_min": 0, "buy_price_min_date": "0001-01-01T00:00:00", "buy_price_max": 0, "buy_price_max_date": "0001-01-01T00:00:00"}, {"item_id": "T5_ROCK", "city": "Bridgewatch", "quality": 1, "sell_price_min": 93, "sell_price_min_date": "2025-04-10T03:20:00", "sell_price_max": 105, "sell_price_max_date": "2025-04-10T03:20:00", "buy_price_min": 1, "buy_price_min_date": "2025-04-10T03:20:00", "buy_price_max": 92, "buy_price_max_date": "2025-04-10T03:20:00"}, {"item_id": "T5_ROCK", "city": "Caerleon", "quality": 1, "sell_price_min": 31, "sell_price_min_date": "2025-04-09T23:10:00", "sell_price_max": 35, "sell_price_max_date": "2025-04-09T23:10:00", "buy_price_min": 0, "buy_price_min_date": "0001-01-01T00:00:00", "buy_price_max": 0, "buy_price_max_date": "0001-01-01T00:00:00"}, {"item_id": "T5_ROCK", "city": "Fort Sterling", "quality": 1, "sell_price_min": 42, "sell_price_min_date": "2025-04-10T01:35:00", "sell_price_max": 76, "sell_price_max_date": "2025-04-10T01:35:00", "buy_price_min": 12, "buy_price_min_date": "2025-04-10T01:35:00", "buy_price_max": 40, "buy_price_max_date": "2025-04-10T01:35:00"}, {"item_id": "T5_ROCK", "city": "Lymhurst", "quality": 1, "sell_price_min": 49, "sell_price_min_date": "2025-04-10T00:20:00", "sell_price_max": 99, "sell_price_max_date": "2025-04-10T00:20:00", "buy_price_min": 26, "buy_price_min_date": "2025-04-10T00:20:00", "buy_price_max": 47, "buy_price_max_date": "2025-04-10T00:20:00"}, {"item_id": "T5_ROCK", "city": "Martlock", "quality": 1, "sell_price_min": 73, "sell_price_min_date": "2025-04-10T00:15:00", "sell_price_max": 73, "sell_price_max_date": "2025-04-10T00:15:00", "buy_price_min": 1, "buy_price_min_date": "2025-04-09T10:25:00", "buy_price_max": 69, "buy_price_max_date": "2025-04-09T10:25:00"}, {"item_id": "T5_ROCK", "city": "Thetford", "quality": 1, "sell_price_min": 35, "sell_price_min_date": "2025-04-10T02:10:00", "sell_price_max": 36, "sell_price_max_date": "2025-04-10T02:10:00", "buy_price_min": 22, "buy_price_min_date": "2025-04-10T01:25:00", "buy_price_max": 33, "buy_price_max_date": "2025-04-10T01:25:00"}, {"item_id": "T5_WOOD", "city": "Black Market", "quality": 1, "sell_price_min": 0, "sell_price_min_date": "0001-01-01T00:00:00", "sell_price_max": 0, "sell_price_max_date": "0001-01-01T00:00:00", "buy_price_min": 0, "buy_price_min_date": "0001-01-01T00:00:00", "buy_price_max": 0, "buy_price_max_date": "0001-01-01T00:00:00"}, {"item_id": "T5_WOOD", "city": "Bridgewatch", "quality": 1, "sell_price_min": 180, "sell_price_min_date": "2025-04-09T13:40:00", "sell_price_max": 202, "sell_price_max_date": "2025-04-09T13:40:00", "buy_price_min": 7, "buy_price_min_date": "2025-04-09T13:40:00", "buy_price_max": 178, "buy_price_max_date": "2025-04-09T13:40:00"}, {"item_id": "T5_WOOD", "city": "Caerleon", "quality": 1, "sell_price_min": 0, "sell_price_min_date": "0001-01-01T00:00:00", "sell_price_max": 0, "sell_price_max_date": "0001-01-01T00:00:00", "buy_price_min": 0, "buy_price_min_date": "0001-01-01T00:00:00", "buy_price_max": 0, "buy_price_max_date": "0001-01-01T00:00:00"}, {"item_id": "T5_WOOD", "city": "Fort Sterling", "quality": 1, "sell_price_min": 26891, "sell_price_min_date": "2025-04-10T01:40:00", "sell_price_max": 26891, "sell_price_max_date": "2025-04-10T01:40:00", "buy_price_min": 14, "buy_price_min_date": "2025-04-09T15:25:00", "buy_price_max": 210, "buy_price_max_date": "2025-04-09T15:25:00"}, {"item_id": "T5_WOOD", "city": "Lymhurst", "quality": 1, "sell_price_min": 215, "sell_price_min_date": "2025-04-10T03:05:00", "sell_price_max": 225, "sell_price_max_date": "2025-04-10T03:05:00", "buy_price_min": 31, "buy_price_min_date": "2025-04-10T03:10:00", "buy_price_max": 199, "buy_price_max_date": "2025-04-10T03:10:00"}, {"item_id": "T5_WOOD", "city": "Martlock", "quality": 1, "sell_price_min": 0, "sell_price_min_date": "0001-01-01T00:00:00", "sell_price_max": 0, "sell_price_max_date": "0001-01-01T00:00:00", "buy_price_min": 0, "buy_price_min_date": "0001-01-01T00:00:00", "buy_price_max": 0, "buy_price_max_date": "0001-01-01T00:00:00"}, {"item_id": "T5_WOOD", "city": "Thetford", "quality": 1, "sell_price_min": 207, "sell_price_min_date": "2025-04-09T14:05:00", "sell_price_max": 207, "sell_price_max_date": "2025-04-09T14:05:00", "buy_price_min": 0, "buy_price_min_date": "0001-01-01T00:00:00", "buy_price_max": 0, "buy_price_max_date": "0001-01-01T00:00:00"}]}