{"timestamp": 1743824999.4587379, "key_args_repr": "['history', 'T4_FIBER,T4_HIDE,T4_ORE,T4_ROCK,T4_WOOD,T5_FIBER,T5_HIDE,T5_ORE,T5_ROCK,T5_WOOD', 'Black Market,Bridgewatch,Caerleon,Fort Sterling,Lymhurst,Martlock,Thetford', '1', '2025-04-04', '24']", "data": [{"location": "Bridgewatch", "item_id": "T4_FIBER", "quality": 1, "data": [{"item_count": 30867, "avg_price": 76, "timestamp": "2025-04-03T00:00:00"}, {"item_count": 76714, "avg_price": 75, "timestamp": "2025-04-04T00:00:00"}]}, {"location": "Bridgewatch", "item_id": "T4_HIDE", "quality": 1, "data": [{"item_count": 179222, "avg_price": 57, "timestamp": "2025-04-03T00:00:00"}, {"item_count": 72256, "avg_price": 47, "timestamp": "2025-04-04T00:00:00"}]}, {"location": "Bridgewatch", "item_id": "T4_ORE", "quality": 1, "data": [{"item_count": 30927, "avg_price": 78, "timestamp": "2025-04-03T00:00:00"}, {"item_count": 59243, "avg_price": 79, "timestamp": "2025-04-04T00:00:00"}]}, {"location": "Bridgewatch", "item_id": "T5_FIBER", "quality": 1, "data": [{"item_count": 22980, "avg_price": 310, "timestamp": "2025-04-03T00:00:00"}, {"item_count": 35213, "avg_price": 291, "timestamp": "2025-04-04T00:00:00"}]}, {"location": "Bridgewatch", "item_id": "T5_HIDE", "quality": 1, "data": [{"item_count": 77140, "avg_price": 421, "timestamp": "2025-04-03T00:00:00"}, {"item_count": 126678, "avg_price": 418, "timestamp": "2025-04-04T00:00:00"}]}, {"location": "Bridgewatch", "item_id": "T5_ORE", "quality": 1, "data": [{"item_count": 20224, "avg_price": 285, "timestamp": "2025-04-03T00:00:00"}, {"item_count": 36108, "avg_price": 286, "timestamp": "2025-04-04T00:00:00"}]}, {"location": "Bridgewatch", "item_id": "T5_WOOD", "quality": 1, "data": [{"item_count": 10041, "avg_price": 180, "timestamp": "2025-04-03T00:00:00"}, {"item_count": 19792, "avg_price": 179, "timestamp": "2025-04-04T00:00:00"}]}, {"location": "Caerleon", "item_id": "T4_HIDE", "quality": 1, "data": [{"item_count": 1545, "avg_price": 50, "timestamp": "2025-04-03T00:00:00"}]}, {"location": "Caerleon", "item_id": "T5_HIDE", "quality": 1, "data": [{"item_count": 1963, "avg_price": 400, "timestamp": "2025-04-03T00:00:00"}]}, {"location": "Fort Sterling", "item_id": "T4_FIBER", "quality": 1, "data": [{"item_count": 18844, "avg_price": 87, "timestamp": "2025-04-03T00:00:00"}, {"item_count": 54246, "avg_price": 82, "timestamp": "2025-04-04T00:00:00"}]}, {"location": "Fort Sterling", "item_id": "T4_ORE", "quality": 1, "data": [{"item_count": 102210, "avg_price": 97, "timestamp": "2025-04-03T00:00:00"}, {"item_count": 158375, "avg_price": 88, "timestamp": "2025-04-04T00:00:00"}]}, {"location": "Fort Sterling", "item_id": "T5_FIBER", "quality": 1, "data": [{"item_count": 13567, "avg_price": 275, "timestamp": "2025-04-03T00:00:00"}, {"item_count": 49896, "avg_price": 279, "timestamp": "2025-04-04T00:00:00"}]}, {"location": "Lymhurst", "item_id": "T4_FIBER", "quality": 1, "data": [{"item_count": 25644, "avg_price": 92, "timestamp": "2025-04-03T00:00:00"}, {"item_count": 57092, "avg_price": 93, "timestamp": "2025-04-04T00:00:00"}]}, {"location": "Lymhurst", "item_id": "T4_ORE", "quality": 1, "data": [{"item_count": 15988, "avg_price": 81, "timestamp": "2025-04-03T00:00:00"}, {"item_count": 30955, "avg_price": 80, "timestamp": "2025-04-04T00:00:00"}]}, {"location": "Lymhurst", "item_id": "T5_FIBER", "quality": 1, "data": [{"item_count": 25741, "avg_price": 310, "timestamp": "2025-04-03T00:00:00"}, {"item_count": 66959, "avg_price": 317, "timestamp": "2025-04-04T00:00:00"}]}, {"location": "Lymhurst", "item_id": "T5_HIDE", "quality": 1, "data": [{"item_count": 51423, "avg_price": 400, "timestamp": "2025-04-03T00:00:00"}, {"item_count": 134048, "avg_price": 394, "timestamp": "2025-04-04T00:00:00"}]}, {"location": "Lymhurst", "item_id": "T5_ORE", "quality": 1, "data": [{"item_count": 13408, "avg_price": 291, "timestamp": "2025-04-03T00:00:00"}, {"item_count": 35018, "avg_price": 290, "timestamp": "2025-04-04T00:00:00"}]}, {"location": "Lymhurst", "item_id": "T5_ROCK", "quality": 1, "data": [{"item_count": 7560, "avg_price": 58, "timestamp": "2025-04-03T00:00:00"}, {"item_count": 21779, "avg_price": 56, "timestamp": "2025-04-04T00:00:00"}]}, {"location": "Lymhurst", "item_id": "T5_WOOD", "quality": 1, "data": [{"item_count": 34329, "avg_price": 227, "timestamp": "2025-04-03T00:00:00"}, {"item_count": 75993, "avg_price": 228, "timestamp": "2025-04-04T00:00:00"}]}, {"location": "Martlock", "item_id": "T4_FIBER", "quality": 1, "data": [{"item_count": 41720, "avg_price": 72, "timestamp": "2025-04-03T00:00:00"}, {"item_count": 44176, "avg_price": 76, "timestamp": "2025-04-04T00:00:00"}]}, {"location": "Martlock", "item_id": "T4_ORE", "quality": 1, "data": [{"item_count": 26890, "avg_price": 84, "timestamp": "2025-04-03T00:00:00"}, {"item_count": 69600, "avg_price": 83, "timestamp": "2025-04-04T00:00:00"}]}, {"location": "Martlock", "item_id": "T4_ROCK", "quality": 1, "data": [{"item_count": 100034, "avg_price": 17, "timestamp": "2025-04-03T00:00:00"}, {"item_count": 32421, "avg_price": 9, "timestamp": "2025-04-04T00:00:00"}]}, {"location": "Martlock", "item_id": "T4_WOOD", "quality": 1, "data": [{"item_count": 47537, "avg_price": 72, "timestamp": "2025-04-03T00:00:00"}, {"item_count": 18904, "avg_price": 70, "timestamp": "2025-04-04T00:00:00"}]}, {"location": "Martlock", "item_id": "T5_FIBER", "quality": 1, "data": [{"item_count": 20781, "avg_price": 269, "timestamp": "2025-04-03T00:00:00"}, {"item_count": 30511, "avg_price": 287, "timestamp": "2025-04-04T00:00:00"}]}, {"location": "Martlock", "item_id": "T5_HIDE", "quality": 1, "data": [{"item_count": 42817, "avg_price": 473, "timestamp": "2025-04-03T00:00:00"}, {"item_count": 84747, "avg_price": 455, "timestamp": "2025-04-04T00:00:00"}]}, {"location": "Martlock", "item_id": "T5_ORE", "quality": 1, "data": [{"item_count": 33148, "avg_price": 301, "timestamp": "2025-04-03T00:00:00"}, {"item_count": 22847, "avg_price": 294, "timestamp": "2025-04-04T00:00:00"}]}, {"location": "Martlock", "item_id": "T5_ROCK", "quality": 1, "data": [{"item_count": 16705, "avg_price": 64, "timestamp": "2025-04-03T00:00:00"}, {"item_count": 14054, "avg_price": 64, "timestamp": "2025-04-04T00:00:00"}]}, {"location": "Martlock", "item_id": "T5_WOOD", "quality": 1, "data": [{"item_count": 20075, "avg_price": 172, "timestamp": "2025-04-03T00:00:00"}, {"item_count": 38221, "avg_price": 173, "timestamp": "2025-04-04T00:00:00"}]}, {"location": "Thetford", "item_id": "T4_FIBER", "quality": 1, "data": [{"item_count": 77335, "avg_price": 104, "timestamp": "2025-04-03T00:00:00"}, {"item_count": 114932, "avg_price": 90, "timestamp": "2025-04-04T00:00:00"}]}, {"location": "Thetford", "item_id": "T4_ORE", "quality": 1, "data": [{"item_count": 35323, "avg_price": 103, "timestamp": "2025-04-03T00:00:00"}, {"item_count": 157565, "avg_price": 135, "timestamp": "2025-04-04T00:00:00"}]}, {"location": "Thetford", "item_id": "T5_ORE", "quality": 1, "data": [{"item_count": 32549, "avg_price": 319, "timestamp": "2025-04-03T00:00:00"}, {"item_count": 52251, "avg_price": 322, "timestamp": "2025-04-04T00:00:00"}]}]}